{
    "amecro": "american crow",
    "amegfo": "american goldfinch",
    "ameroo": "american robin",
    "bkccho": "black-capped chickadee",
    "blujao": "blue jay",
    "dowwoo": "downy woodpecker",
    "eawpeo": "eastern-wood pewee",
    "moudoo": "mourning dove",
    "norcao": "northern cardinal",
    "rebwoo": "red-bellied woodpecker",
    "reevir1":  "red-eyed vireo",
    "rewblo": "red-winged blackbird",
    "sonspo":"song sparrow",
    "tuftio":"tufted titmouse",
    "whbnuo":"white-breasted nuthatch"
}           
